news_extract/__init__.py
news_extract/news_extract.py
news_extract/striprtf2.py
news_extract-1.0.2.dist-info/DESCRIPTION.rst
news_extract-1.0.2.dist-info/METADATA
news_extract-1.0.2.dist-info/RECORD
news_extract-1.0.2.dist-info/WHEEL
news_extract-1.0.2.dist-info/metadata.json
news_extract-1.0.2.dist-info/top_level.txt
